odoo10_addon_openeducat_erp-10.0.3.0.0-py2.7-nspkg.pth
odoo/addons/openeducat_erp/README.rst
odoo/addons/openeducat_erp/__init__.py
odoo/addons/openeducat_erp/__manifest__.py
odoo/addons/openeducat_erp/doc/changelog.rst
odoo/addons/openeducat_erp/static/description/assignment.png
odoo/addons/openeducat_erp/static/description/attendance.png
odoo/addons/openeducat_erp/static/description/blog.png
odoo/addons/openeducat_erp/static/description/class.png
odoo/addons/openeducat_erp/static/description/dashboard.png
odoo/addons/openeducat_erp/static/description/enrollment.png
odoo/addons/openeducat_erp/static/description/events.png
odoo/addons/openeducat_erp/static/description/exam.png
odoo/addons/openeducat_erp/static/description/faculty.png
odoo/addons/openeducat_erp/static/description/financial.png
odoo/addons/openeducat_erp/static/description/icon.png
odoo/addons/openeducat_erp/static/description/index.html
odoo/addons/openeducat_erp/static/description/media.png
odoo/addons/openeducat_erp/static/description/news.png
odoo/addons/openeducat_erp/static/description/openeducat_erp_banner.jpg
odoo/addons/openeducat_erp/static/description/openeducat_logo.png
odoo/addons/openeducat_erp/static/description/reporting.png
odoo/addons/openeducat_erp/static/description/result.png
odoo/addons/openeducat_erp/static/description/session.png
odoo/addons/openeducat_erp/static/description/student.png
odoo10_addon_openeducat_erp-10.0.3.0.0.dist-info/DESCRIPTION.rst
odoo10_addon_openeducat_erp-10.0.3.0.0.dist-info/METADATA
odoo10_addon_openeducat_erp-10.0.3.0.0.dist-info/RECORD
odoo10_addon_openeducat_erp-10.0.3.0.0.dist-info/WHEEL
odoo10_addon_openeducat_erp-10.0.3.0.0.dist-info/metadata.json
odoo10_addon_openeducat_erp-10.0.3.0.0.dist-info/namespace_packages.txt
odoo10_addon_openeducat_erp-10.0.3.0.0.dist-info/top_level.txt
