Metadata-Version: 2.0
Name: odoo10-addon-openeducat-erp
Version: 10.0.3.0.0
Summary: Manage Students, Faculties and Education Institute
Home-page: http://www.openeducat.org
Author: Tech Receptives
Author-email: UNKNOWN
License: LGPL-3
Platform: UNKNOWN
Classifier: Programming Language :: Python :: 2.7
Classifier: Framework :: Odoo
Classifier: License :: OSI Approved :: GNU Lesser General Public License v3 (LGPLv3)
Requires-Dist: odoo (<10.1dev,>=10.0)
Requires-Dist: odoo10-addon-openeducat-activity
Requires-Dist: odoo10-addon-openeducat-admission
Requires-Dist: odoo10-addon-openeducat-assignment
Requires-Dist: odoo10-addon-openeducat-attendance
Requires-Dist: odoo10-addon-openeducat-exam
Requires-Dist: odoo10-addon-openeducat-library
Requires-Dist: odoo10-addon-openeducat-parent
Requires-Dist: odoo10-addon-openeducat-support
Requires-Dist: odoo10-addon-openeducat-timetable
Requires-Dist: odoo10-addon-web-openeducat
